[
    {
        "achievement": "MD Appreciation Award",
        "description": "Honoured with MD Appreciatioin award by honourable MD at Samsung Research, Noida, for developing SRI-N Satyapan.",
        "link": ""
    },
    {
        "achievement": "Implemented van Emde Boas Tree",
        "description": "1st time correct implementation in python in the History",
        "link": "https://github.com/stopslavery404/van-Emde-Boas-Tree"
    },
    {
        "achievement": "World Programming Championship - IIT Mumbai",
        "description": "Rank 69 | Certificate no 99695",
        "link": ""
    },
    {
        "achievement": "Gold in HackFest 2020",
        "description": "Rank 29 | 8051  Rating 2042.08 from 1500",
        "link": "https://www.hackerrank.com/results/hackerrank-hackfest-2020/stopslavery404"
    },
    {
        "achievement": "GATE 2021",
        "description": "Got AIR 5648",
        "link": "/static/gate2021.png"
    },
    {
        "achievement": "CodeVita Season 9",
        "description": "Cleared Round 1 with Rank 1042",
        "link": ""
    },
    {
        "achievement": "CodeVita Season 9",
        "description": "Got International 242 in Round 2",
        "link": ""
    },
    {
        "achievement": "CodeVita Season 10",
        "description": "Got International 426 in Round 1",
        "link": ""
    },
    {
        "achievement": "Hack the Interview III",
        "description": "Rank(73 | 919)",
        "link": "https://www.hackerrank.com/results/hack-the-interview-iv/stopslavery404"
    },
    {
        "achievement": "Hack the Interview IV (Asia Pacific)",
        "description": "Rank(100 | 4353)",
        "link": "https://www.hackerrank.com/results/hack-the-interview-iv-apac/stopslavery404"
    },
    {
        "achievement": "Hack the Interview IV (U.S.) ",
        "description": "Rank( 65 | 1217) ",
        "link": "https://www.hackerrank.com/results/hack-the-interview-iv/stopslavery404?h_r=profile"
    },
    {
        "achievement": "Hackerrank Algorithms",
        "description": "Rank 1026/ 2219538",
        "link": "https://www.hackerrank.com/leaderboard?filter=stopslavery404&filter_on=hacker&page=1&track=algorithms&type=practice"
    },
    {
        "achievement": "Hackerrank Data Structures ",
        "description": "Rank 540| 931788",
        "link": "https://www.hackerrank.com/leaderboard?filter=stopslavery404&filter_on=hacker&page=1&track=data-structures&type=practice"
    },
    {
        "achievement": "Hackerrank Python Practice",
        "description": "Rank 1",
        "link": "https://www.hackerrank.com/leaderboard?filter=stopslavery404&filter_on=hacker&page=1&track=python&type=practice"
    }
]